{
  "legislative_session": "2025-2026",
  "identifier": "HF 192",
  "title": "A bill for an act relating to the responsibility and liability of property owners for public places in cities and including effective date provisions.",
  "from_organization": "~{\"classification\": \"lower\"}",
  "classification": [
    "bill"
  ],
  "subject": [
    "city government",
    "civil liability",
    "public property",
    "real property"
  ],
  "abstracts": [],
  "other_titles": [],
  "other_identifiers": [],
  "actions": [
    {
      "description": "Introduced, referred to Judiciary.",
      "date": "2025-02-03",
      "organization_id": "~{\"classification\": \"lower\"}",
      "classification": [
        "introduction",
        "referral-committee"
      ],
      "related_entities": [],
      "_processing": {
        "log_file_created": "2025-10-24T05:05:07Z"
      }
    },
    {
      "description": "Subcommittee: Lohse, Croken and Holt.",
      "date": "2025-02-06",
      "organization_id": "~{\"classification\": \"lower\"}",
      "classification": [],
      "related_entities": [],
      "_processing": {
        "log_file_created": "2025-10-24T05:05:07Z"
      }
    },
    {
      "description": "Subcommittee Meeting: 02/11/2025 12:30PM RM 103.",
      "date": "2025-02-10",
      "organization_id": "~{\"classification\": \"legislature\"}",
      "classification": [],
      "related_entities": [],
      "_processing": {
        "log_file_created": "2025-10-24T05:05:07Z"
      }
    },
    {
      "description": "Subcommittee recommends passage.",
      "date": "2025-02-11",
      "organization_id": "~{\"classification\": \"legislature\"}",
      "classification": [
        "committee-passage-favorable"
      ],
      "related_entities": [],
      "_processing": {
        "log_file_created": "2025-10-24T05:05:07Z"
      }
    }
  ],
  "sponsorships": [
    {
      "name": "LOHSE",
      "classification": "primary",
      "entity_type": "person",
      "primary": true,
      "person_id": "~{\"name\": \"LOHSE\"}",
      "organization_id": null
    }
  ],
  "related_bills": [],
  "versions": [
    {
      "note": "Introduced",
      "links": [
        {
          "url": "https://www.legis.iowa.gov/docs/publications/LGI/91/attachments/HF192.html",
          "media_type": "text/html"
        },
        {
          "url": "https://www.legis.iowa.gov/docs/publications/LGI/91/HF192.pdf",
          "media_type": "application/pdf"
        }
      ],
      "date": "",
      "classification": ""
    }
  ],
  "documents": [],
  "citations": [],
  "sources": [
    {
      "url": "https://www.legis.iowa.gov/legislation/billTracking/billHistory?billName=HF 192&ga=91",
      "note": ""
    }
  ],
  "extras": {},
  "jurisdiction": {
    "id": "ocd-jurisdiction/country:us/state:ia/government",
    "name": "Iowa",
    "classification": "state",
    "division_id": "ocd-division/country:us/state:ia"
  },
  "_processing": {
    "logs_latest_update": "2025-10-24T05:05:07Z"
  }
}